[{"_id":"e90cbdde-ff0f-469f-8044-35e091cb3d90","title":"","description":"","questions":[{"_id":"001ef0e8-cc99-425b-9722-a3a15d7fbb68","title":"Untitled Question","description":"","type":"QUESTION_PARAGRAPH","content":{"placeHolder":"","min":0,"max":1024}},{"_id":"5653beab-d643-443e-aa98-b7a4b82fa38b","title":"Untitled Question","description":"","type":"QUESTION_TEXT","content":{"placeHolder":"","inputType":"INPUT_TEXT","min":0,"max":512}},{"_id":"575804aa-e010-4bac-a867-b990f4c14f9f","title":"Untitled Question","description":"","content":{"choices":["Option 1","Option 2","Option 3","Option 4","Option 5","Option 6"]},"type":"QUESTION_RADIO_GROUP"},{"_id":"8f7c198e-328b-4e5f-8587-e290c3cb06b8","title":"Untitled Question","description":"","content":{"choices":["Option 1","Option 2","Option 3","Option 4"]},"type":"QUESTION_CHECKBOX"},{"_id":"d45a61c0-faee-4009-adee-c53c1b6c4e4c","title":"Untitled Question","description":"","content":{"choices":["Option 1","Option 2","Option 3","Option 4","Option 5"]},"type":"QUESTION_DROPDOWN"}]}]